discord_boteasy/__init__.py
discord_boteasy/all.py
discord_boteasy/runclient.py
discord_boteasy/version.py
discord_boteasy-0.0.2.dist-info/METADATA
discord_boteasy-0.0.2.dist-info/WHEEL
discord_boteasy-0.0.2.dist-info/top_level.txt
discord_boteasy-0.0.2.dist-info/RECORD
