Metadata-Version: 2.4
Name: discord_boteasy
Version: 0.0.2
Summary: Create Discord Bots With Ease
Author-email: SH_Dev <glock.96.beamed@gmail.com>
Requires-Python: >=3.7
Dynamic: requires-python
